babar/__init__.py
babar/cli.py
babar/error.py
babar/models.py
babar/pg.py
babar/examples/__init__.py
babar/examples/pystring.py
pybabar-0.1.0a3.dist-info/LICENSE
pybabar-0.1.0a3.dist-info/METADATA
pybabar-0.1.0a3.dist-info/WHEEL
pybabar-0.1.0a3.dist-info/entry_points.txt
pybabar-0.1.0a3.dist-info/top_level.txt
pybabar-0.1.0a3.dist-info/RECORD
