Metadata-Version: 2.1
Name: pybabar
Version: 0.1.0a3
Summary: babar is a library for automatically generating Postgres extensions from absolutely any Python object.
Home-page: https://github.com/Florents-Tselai/babar
Author: Florents Tselai
Author-email: florents@tselai.com
License: Apache License, Version 2.0
Project-URL: Documentation, https://github.com/Florents-Tselai/babar
Project-URL: Issues, https://github.com/Florents-Tselai/babar/issues
Project-URL: CI, https://github.com/Florents-Tselai/babar/actions
Project-URL: Changelog, https://github.com/Florents-Tselai/babar/releases
Requires-Python: >=3.7
License-File: LICENSE
Requires-Dist: click
Requires-Dist: click-default-group >=1.2.3
Requires-Dist: pydantic >=1.10.2
Requires-Dist: setuptools
Requires-Dist: pip
Provides-Extra: test
Requires-Dist: pytest ; extra == 'test'
Requires-Dist: pytest-cov ; extra == 'test'
Requires-Dist: black ; extra == 'test'
Requires-Dist: ruff ; extra == 'test'
Requires-Dist: click ; extra == 'test'
